kdot_mustard/__init__.py
kdot_mustard/_calculate.py
kdot_mustard/_visual.py
kdot_mustard/kdot_mustard.py
kdot_mustard/img/bossman.gif
kdot_mustard/img/kendrick.jpeg
kdot_mustard/img/test.jpg
kdot_mustard-1.0.0.dist-info/METADATA
kdot_mustard-1.0.0.dist-info/WHEEL
kdot_mustard-1.0.0.dist-info/licenses/LICENSE
kdot_mustard-1.0.0.dist-info/RECORD
