Metadata-Version: 2.4
Name: kdot-mustard
Version: 1.0.0
Summary: The ultimate hotdog condiment
Project-URL: Repo, https://github.com/KrashKart/kdot
Author-email: KrashKart <shootandscoot222@gmail.com>
License-Expression: MIT
License-File: LICENSE
Classifier: Operating System :: Microsoft :: Windows
Classifier: Programming Language :: Python :: 3.11
Requires-Python: >=3.11
Requires-Dist: numpy
Requires-Dist: pillow
Requires-Dist: tqdm
